calweek.py
calweek-0.5.0.dist-info/LICENSE.txt
calweek-0.5.0.dist-info/METADATA
calweek-0.5.0.dist-info/WHEEL
calweek-0.5.0.dist-info/top_level.txt
calweek-0.5.0.dist-info/RECORD
