Metadata-Version: 2.1
Name: calweek
Version: 0.5.0
Summary: Objects representing a (non-ISO) week
Home-page: http://github.com/wonkyweirdy/calweek
Author: Ray Burr
Author-email: ryb@nightmare.com
License: BSD
Platform: UNKNOWN
Classifier: Development Status :: 3 - Alpha
Classifier: Intended Audience :: Developers
Classifier: License :: OSI Approved :: BSD License
Classifier: Operating System :: OS Independent
Classifier: Programming Language :: Python
Classifier: Programming Language :: Python :: 2.7
Classifier: Programming Language :: Python :: 3
Classifier: Topic :: Software Development :: Libraries :: Python Modules
